mangareader_api/__init__.py
mangareader_api/chapter.py
mangareader_api/constants.py
mangareader_api/manga.py
mangareader_api-1.0.0.dist-info/LICENSE
mangareader_api-1.0.0.dist-info/METADATA
mangareader_api-1.0.0.dist-info/WHEEL
mangareader_api-1.0.0.dist-info/top_level.txt
mangareader_api-1.0.0.dist-info/RECORD
