Metadata-Version: 2.1
Name: mangareader-api
Version: 1.0.0
Summary: An Unoffical Python API for mangareader.to
Home-page: https://github.com/john-erinjery/mangareader-api/
Author: John Erinjery
Author-email: jancyvinod415@gmail.com
License: MIT
Classifier: Development Status :: 4 - Beta
Classifier: Environment :: Console
Classifier: Intended Audience :: Customer Service
Classifier: License :: OSI Approved :: MIT License
Classifier: Natural Language :: English
Classifier: Operating System :: OS Independent
Classifier: Programming Language :: Python :: 3.10
Classifier: Topic :: Internet
Classifier: Topic :: Software Development :: Libraries
Classifier: Topic :: Software Development :: Libraries :: Python Modules
Classifier: Topic :: Utilities
Requires-Python: >=3.10
License-File: LICENSE
Requires-Dist: setuptools
Requires-Dist: lxml (==4.9.2)
Requires-Dist: beautifulsoup4 (>=4.11.2)
Requires-Dist: requests (==2.28.2)
